gimpify/__init__.py
gimpify/helpers.py
gimpify/montage.py
tests/__init__.py
tests/context.py
tests/test_montage.py
gimpify_watxaut-0.0.1.dist-info/LICENCE
gimpify_watxaut-0.0.1.dist-info/METADATA
gimpify_watxaut-0.0.1.dist-info/WHEEL
gimpify_watxaut-0.0.1.dist-info/top_level.txt
gimpify_watxaut-0.0.1.dist-info/RECORD
